jikipedia/__init__.py
jikipedia/xid.py
jikipedia-0.6.0.dev0.dist-info/LICENSE
jikipedia-0.6.0.dev0.dist-info/METADATA
jikipedia-0.6.0.dev0.dist-info/WHEEL
jikipedia-0.6.0.dev0.dist-info/top_level.txt
jikipedia-0.6.0.dev0.dist-info/RECORD
